{"runtime_in_sec": 17688.14013814926, "n": 7, "instances": [["(a=52, b=80, modulus=83)", [40, 80], [81, 36]], ["(a=2, b=75, modulus=103)", [50, 66], [92, 24]]], "choice_metric": "gate_depth", "results": {"gate_count": [4977328, 5092376], "gate_depth": [3335077, 3449277], "cz_count": [1887472, 1941337], "cz_depth": [1699928, 1757060], "qubit_count": [31, 31], "gate_count_average": 5034852.0, "gate_depth_average": 3392177.0, "cz_count_average": 1914404.5, "cz_depth_average": 1728494.0}, "seed": 0, "num_instances": 2}